friktionutils/.pytest_cache/.gitignore
friktionutils/.pytest_cache/CACHEDIR.TAG
friktionutils/.pytest_cache/README.md
friktionutils/.pytest_cache/v/cache/lastfailed
friktionutils/.pytest_cache/v/cache/nodeids
friktionutils/.pytest_cache/v/cache/stepwise
friktionutils/__init__.py
friktionutils/btc_call.csv
friktionutils/btc_put.csv
friktionutils/metrics.py
friktionutils/options.py
friktionutils/sol_put.csv
friktionutils/test_metrics.py
friktionutils/test_options.py
friktion_research_utils-0.0.41.dist-info/WHEEL
friktion_research_utils-0.0.41.dist-info/METADATA
friktion_research_utils-0.0.41.dist-info/RECORD
