Metadata-Version: 2.1
Name: friktion-research-utils
Version: 0.0.41
Summary: Friktion research toolkit
Home-page: https://app.friktion.fi
License: MIT
Author: thiccythot
Requires-Python: >=3.8,<4.0
Classifier: License :: OSI Approved :: MIT License
Classifier: Programming Language :: Python :: 3
Classifier: Programming Language :: Python :: 3.10
Classifier: Programming Language :: Python :: 3.8
Classifier: Programming Language :: Python :: 3.9
Requires-Dist: numpy (>=1.22.3,<2.0.0)
Requires-Dist: pandas (>=1.4.2,<2.0.0)
Requires-Dist: pytest (>=7.1.2,<8.0.0)
Requires-Dist: requests (>=2.27.1,<3.0.0)
Project-URL: Repository, https://github.com/friktion-labs/blockdata
